Metadata-Version: 1.0
Name: rdsutilsfinal
Version: 0.0.6
Summary: My first Python package
Home-page: UNKNOWN
Author: johnson
Author-email: johnssimon007@email.com
License: UNKNOWN
Platform: UNKNOWN
